alhazen/__init__.py
alhazen/alhazen.py
alhazen/feature_collector.py
alhazen/features.py
alhazen/generator.py
alhazen/grammar_transformation.py
alhazen/helper.py
alhazen/input.py
alhazen/input_specifications.py
alhazen/learner.py
alhazen/oracle.py
alhazen/performance_evaluator.py
alhazen/requirementExtractionDT/__init__.py
alhazen/requirementExtractionDT/features.py
alhazen/requirementExtractionDT/requirements.py
alhazen/requirementExtractionDT/treetools.py
alhazen_formalizations/__init__.py
alhazen_formalizations/calculator.py
alhazen_formalizations/heartbeat.py
alhazen_py-0.0.3.dist-info/LICENSE
alhazen_py-0.0.3.dist-info/METADATA
alhazen_py-0.0.3.dist-info/WHEEL
alhazen_py-0.0.3.dist-info/entry_points.txt
alhazen_py-0.0.3.dist-info/top_level.txt
alhazen_py-0.0.3.dist-info/RECORD
