Metadata-Version: 2.1
Name: alhazen-py
Version: 0.0.3
Summary: Python version of the debugging tool Alhazen
Home-page: https://github.com/martineberlein/alhazen-py
Author: Martin Eberlein
Author-email: martin.eberlein@hu-berlin.de
License: MIT License
Project-URL: Bug Tracker, https://github.com/martineberlein/alhazen-py/issues
Classifier: Intended Audience :: Science/Research
Classifier: License :: OSI Approved :: MIT License
Classifier: Programming Language :: Python :: 3.10
Classifier: Operating System :: OS Independent
Classifier: Topic :: Scientific/Engineering
Classifier: Topic :: Software Development :: Testing
Requires-Python: >=3.10
License-File: LICENSE
Requires-Dist: fuzzingbook (>=1.1)
Requires-Dist: isla-solver
Requires-Dist: islearn
Requires-Dist: lightgbm (>=3.3.2)
Requires-Dist: z3-solver (>=4.10.2.0)
Requires-Dist: pandas
Requires-Dist: numpy
Requires-Dist: scikit-learn
Provides-Extra: dev
Requires-Dist: pytest (>=7.2.0) ; extra == 'dev'
Requires-Dist: twine ; extra == 'dev'
Requires-Dist: black ; extra == 'dev'
